PlotStream/__init__.py
PlotStream/app.py
PlotStream/data_proc.py
PlotStream/funcs_def.py
plotstream-0.2.6.dist-info/LICENSE
plotstream-0.2.6.dist-info/METADATA
plotstream-0.2.6.dist-info/WHEEL
plotstream-0.2.6.dist-info/top_level.txt
plotstream-0.2.6.dist-info/RECORD
