Metadata-Version: 2.2
Name: plotstream
Version: 0.2.6
Summary: plotstream is a Python package that allows you to stream plots to a web browser using Streamlit.
Author-email: blu3c0ral <blu3c0ral@protonmail.ch>
Project-URL: Homepage, https://github.com/blu3c0ral/PlotStream
Project-URL: Bug Tracker, https://github.com/blu3c0ral/PlotStream/issues
Classifier: Programming Language :: Python :: 3
Classifier: License :: OSI Approved :: MIT License
Classifier: Operating System :: OS Independent
Requires-Python: >=3.7
License-File: LICENSE
Requires-Dist: streamlit
Requires-Dist: pandas
Requires-Dist: numpy
Requires-Dist: dill
Requires-Dist: plotly
Requires-Dist: scipy
